indic_asr_onnx/__init__.py
indic_asr_onnx/transcriber.py
indic_asr_onnx-0.2.1.dist-info/licenses/LICENSE
indic_asr_onnx-0.2.1.dist-info/WHEEL
indic_asr_onnx-0.2.1.dist-info/METADATA
indic_asr_onnx-0.2.1.dist-info/RECORD
