Metadata-Version: 2.4
Name: indic-asr-onnx
Version: 0.2.1
Summary: Quantized IndicConformer ASR models for multiple Indian languages
Keywords: asr,speech-recognition,indic-languages,multilingual,conformer,ctc,rnnt,onnx,quantized
Author: Atharva Verma
Author-email: Atharva Verma <atharva.verma18@gmail.com>
License-Expression: MIT
License-File: LICENSE
Classifier: Development Status :: 3 - Alpha
Classifier: Intended Audience :: Developers
Classifier: Operating System :: OS Independent
Classifier: Programming Language :: Python :: 3.8
Classifier: Topic :: Multimedia :: Sound/Audio :: Speech
Classifier: Topic :: Scientific/Engineering :: Artificial Intelligence
Requires-Dist: torch>=2.0.0
Requires-Dist: torchaudio>=2.0.0
Requires-Dist: onnxruntime>=1.15.0
Requires-Dist: onnxruntime-gpu>=1.15.0
Requires-Dist: numpy>=1.21.0
Requires-Dist: torchcodec
Requires-Dist: uv ; extra == 'dev'
Requires-Dist: twine ; extra == 'dev'
Requires-Python: >=3.8
Project-URL: Homepage, https://github.com/atharva-again/indic-asr-onnx
Project-URL: Issues, https://github.com/atharva-again/indic-asr-onnx/issues
Project-URL: Repository, https://github.com/atharva-again/indic-asr-onnx
Provides-Extra: dev
Provides-Extra: test
